_pyecrt.cpython-313-aarch64-linux-musl.so
ecrt/__init__.py
ecrt/ecrt.py
ecrt/lib/libecrt.so
ecrt-0.0.5.dist-info/METADATA
ecrt-0.0.5.dist-info/WHEEL
ecrt-0.0.5.dist-info/top_level.txt
ecrt-0.0.5.dist-info/RECORD
