Metadata-Version: 2.1
Name: ecrt
Version: 0.0.5
Summary: eC Runtime Library
Home-page: https://ec-lang.org
Author: Jérôme Jacovella-St-Louis, Ecere Corporation
Author-email: jerome@ecere.com
License: BSD-3-Clause
Keywords: eC runtime type-system object-model reflection file-system collections datetime json-parser econ serialization
Classifier: Development Status :: 4 - Beta
Classifier: Intended Audience :: Developers
Classifier: Operating System :: Microsoft :: Windows
Classifier: Operating System :: POSIX :: Linux
Classifier: Operating System :: MacOS
Classifier: Programming Language :: Other
Classifier: Programming Language :: Python :: 3
Classifier: Topic :: File Formats :: JSON
Classifier: Topic :: Software Development :: Internationalization
Classifier: Topic :: Software Development :: Libraries
Requires-Dist: cffi >=1.0.0
